batchbeagle/__init__.py
batchbeagle/config.py
batchbeagle/dplycli.py
batchbeagle/aws/__init__.py
batchbeagle/aws/batch.py
batchbeagle-0.2.0.dist-info/DESCRIPTION.rst
batchbeagle-0.2.0.dist-info/METADATA
batchbeagle-0.2.0.dist-info/RECORD
batchbeagle-0.2.0.dist-info/WHEEL
batchbeagle-0.2.0.dist-info/entry_points.txt
batchbeagle-0.2.0.dist-info/metadata.json
batchbeagle-0.2.0.dist-info/top_level.txt
