Metadata-Version: 2.0
Name: batchbeagle
Version: 0.2.0
Summary: AWS Batch related deployment tools
Home-page: https://github.com/caltechads/batchbeagle
Author: Caltech IMSS ADS
Author-email: imss-ads-staff@caltech.edu
License: UNKNOWN
Keywords: aws,batch
Platform: UNKNOWN
Classifier: Programming Language :: Python :: 2.7
Classifier: Programming Language :: Python :: 3
Requires-Dist: boto3 (>=1.4.4)
Requires-Dist: click (>=6.7)
Requires-Dist: PyYAML (==3.12)
